avstockparser/AVStockParser.py
avstockparser/UniLogger.py
avstockparser/__init__.py
avstockparser/__main__.py
avstockparser-1.1.6.dist-info/LICENSE
avstockparser-1.1.6.dist-info/METADATA
avstockparser-1.1.6.dist-info/WHEEL
avstockparser-1.1.6.dist-info/entry_points.txt
avstockparser-1.1.6.dist-info/top_level.txt
avstockparser-1.1.6.dist-info/zip-safe
avstockparser-1.1.6.dist-info/RECORD
